odoo/addons/widget_list_row_color/README.rst
odoo/addons/widget_list_row_color/__init__.py
odoo/addons/widget_list_row_color/__manifest__.py
odoo/addons/widget_list_row_color/static/description/ejemplo.png
odoo/addons/widget_list_row_color/static/description/icon.png
odoo/addons/widget_list_row_color/static/src/js/list_renderer.js
odoo_addon_widget_list_row_color-16.0.1.0.0.dist-info/METADATA
odoo_addon_widget_list_row_color-16.0.1.0.0.dist-info/WHEEL
odoo_addon_widget_list_row_color-16.0.1.0.0.dist-info/top_level.txt
odoo_addon_widget_list_row_color-16.0.1.0.0.dist-info/RECORD
